<mvc:View xmlns:mvc="sap.ui.core.mvc" controllerName="com.sap.build.standard.untitledPrototype.controller.Page6" xmlns:uxap="sap.uxap" xmlns="sap.m" xmlns:layout="sap.ui.layout" xmlns:form="sap.ui.layout.form" xmlns:core="sap.ui.core">
    <uxap:ObjectPageLayout showTitleInHeaderContent="false" showHeaderContent="true" showEditHeaderButton="false" showFooter="false" class="sapUiSizeCompact">
        <uxap:headerTitle>
            <uxap:ObjectPageHeader objectTitle="Title" objectSubtitle="Description" isObjectIconAlwaysVisible="false" isObjectTitleAlwaysVisible="true" isObjectSubtitleAlwaysVisible="true" showPlaceholder="true" objectImageURI="/build/uilibraries/content/static/image-canvas.svg">
                <uxap:navigationBar>
                    <Bar>
                        <contentLeft>
                            <Button type="Back" press="_onFioriObjectPageHeaderPress"/>
                        </contentLeft>
                        <contentMiddle>
                            <Title text="Producto"/>
                        </contentMiddle>
                        <contentRight/>
                    </Bar>
                </uxap:navigationBar>
                <uxap:actions/>
                <uxap:breadCrumbsLinks/>
            </uxap:ObjectPageHeader>
        </uxap:headerTitle>
        <uxap:headerContent/>
        <uxap:sections>
            <uxap:ObjectPageSection title="Editar">
                <uxap:subSections>
                    <uxap:ObjectPageSubSection title="Editar">
                        <uxap:blocks>
                            <layout:Grid defaultSpan="XL12 L12 M12 S12">
                                <layout:content>
                                    <form:Form>
                                        <form:layout>
                                            <form:ResponsiveGridLayout labelSpanXL="12" labelSpanL="12" labelSpanM="12" labelSpanS="12" adjustLabelSpan="false" emptySpanXL="0" emptySpanL="0" emptySpanM="0" emptySpanS="0" columnsXL="4" columnsL="3" columnsM="2" singleContainerFullSize="false"/>
                                        </form:layout>
                                        <form:formContainers>
                                            <form:FormContainer title="Info">
                                                <form:formElements>
                                                    <form:FormElement>
                                                        <form:label>
                                                            <Label text="Nombre" required="true"/>
                                                        </form:label>
                                                        <form:fields>
                                                            <Input value="{Nombre}" type="Text" showValueHelp="false" enabled="true" visible="true" width="auto" valueHelpOnly="false" required="false" valueStateText="Invalid entry" maxLength="0"/>
                                                        </form:fields>
                                                    </form:FormElement>
                                                    <form:FormElement>
                                                        <form:label>
                                                            <Label text="Precio" required="true"/>
                                                        </form:label>
                                                        <form:fields>
                                                            <Input value="{Precio}" type="Text" showValueHelp="false" enabled="true" visible="true" width="auto" valueHelpOnly="false" required="false" valueStateText="Invalid entry" maxLength="0"/>
                                                        </form:fields>
                                                    </form:FormElement>
                                                    <form:FormElement>
                                                        <form:label>
                                                            <Label text="Cantidad" required="true"/>
                                                        </form:label>
                                                        <form:fields>
                                                            <Input value="{path: 'Cantidad', type: 'sap.ui.model.type.Float', formatOptions: { maxFractionDigits: 2 }}" type="Text" showValueHelp="false" enabled="true" visible="true" width="auto" valueHelpOnly="false" required="false" valueStateText="Invalid entry" maxLength="0"/>
                                                        </form:fields>
                                                    </form:FormElement>
                                                </form:formElements>
                                            </form:FormContainer>
                                            <form:FormContainer title="Caducidad">
                                                <form:formElements>
                                                    <form:FormElement>
                                                        <form:label>
                                                            <Label text="Fecha" required="true"/>
                                                        </form:label>
                                                        <form:fields>
                                                            <DatePicker value="{path: 'Fecha_de_vencimiento', type: 'sap.ui.model.type.Date', formatOptions: { UTC: true, style: 'medium' }}" width="auto" displayFormat="medium" required="false" valueStateText="Invalid entry" enabled="true" visible="true" valueFormat="yyyyMMdd"/>
                                                        </form:fields>
                                                    </form:FormElement>
                                                    <form:FormElement>
                                                        <form:label>
                                                            <Label text="Estado" required="false"/>
                                                        </form:label>
                                                        <form:fields>
                                                            <ComboBox selectedKey="{EstadoCC}" editable="true" enabled="true" visible="true" width="auto" valueState="None" maxWidth="100%" items="{path:'/ProductSet', templateShareable:true}">
                                                                <items>
                                                                    <core:Item text="{EstadoCC}" enabled="true" key="{EstadoCC}"/>
                                                                </items>
                                                            </ComboBox>
                                                        </form:fields>
                                                    </form:FormElement>
                                                </form:formElements>
                                            </form:FormContainer>
                                            <form:FormContainer title="Reservado">
                                                <form:formElements>
                                                    <form:FormElement>
                                                        <form:label>
                                                            <Label text="Reservado" required="false"/>
                                                        </form:label>
                                                        <form:fields>
                                                            <CheckBox text="" selected="{Reservado}" editable="true" enabled="true" visible="true" width="auto" textDirection="Inherit" wrapping="false" useEntireWidth="true"/>
                                                        </form:fields>
                                                    </form:FormElement>
                                                </form:formElements>
                                            </form:FormContainer>
                                        </form:formContainers>
                                    </form:Form>
                                </layout:content>
                            </layout:Grid>
                        </uxap:blocks>
                    </uxap:ObjectPageSubSection>
                </uxap:subSections>
            </uxap:ObjectPageSection>
        </uxap:sections>
        <uxap:footer>
            <OverflowToolbar design="auto">
                <content>
                    <ToolbarSpacer/>
                    <Button text="Save" type="Emphasized" iconFirst="true" width="auto" enabled="true" visible="true" iconDensityAware="false"/>
                    <Button text="Cancel" type="Default" iconFirst="true" width="auto" enabled="true" visible="true" iconDensityAware="false"/>
                </content>
            </OverflowToolbar>
        </uxap:footer>
    </uxap:ObjectPageLayout>
</mvc:View>
